auto_archiver/__main__.py
auto_archiver/core/__init__.py
auto_archiver/core/base_module.py
auto_archiver/core/config.py
auto_archiver/core/consts.py
auto_archiver/core/database.py
auto_archiver/core/enricher.py
auto_archiver/core/extractor.py
auto_archiver/core/feeder.py
auto_archiver/core/formatter.py
auto_archiver/core/media.py
auto_archiver/core/metadata.py
auto_archiver/core/module.py
auto_archiver/core/orchestrator.py
auto_archiver/core/storage.py
auto_archiver/core/validators.py
auto_archiver/modules/antibot_extractor_enricher/__init__.py
auto_archiver/modules/antibot_extractor_enricher/__manifest__.py
auto_archiver/modules/antibot_extractor_enricher/antibot_extractor_enricher.py
auto_archiver/modules/antibot_extractor_enricher/captcha_services/.gitignore
auto_archiver/modules/antibot_extractor_enricher/dropin.py
auto_archiver/modules/antibot_extractor_enricher/dropins/default.py
auto_archiver/modules/antibot_extractor_enricher/dropins/linkedin.py
auto_archiver/modules/antibot_extractor_enricher/dropins/reddit.py
auto_archiver/modules/antibot_extractor_enricher/dropins/tiktok.py
auto_archiver/modules/antibot_extractor_enricher/dropins/vk.py
auto_archiver/modules/api_db/__init__.py
auto_archiver/modules/api_db/__manifest__.py
auto_archiver/modules/api_db/api_db.py
auto_archiver/modules/atlos_feeder_db_storage/__init__.py
auto_archiver/modules/atlos_feeder_db_storage/__manifest__.py
auto_archiver/modules/atlos_feeder_db_storage/atlos_feeder_db_storage.py
auto_archiver/modules/cli_feeder/__manifest__.py
auto_archiver/modules/cli_feeder/cli_feeder.py
auto_archiver/modules/console_db/__init__.py
auto_archiver/modules/console_db/__manifest__.py
auto_archiver/modules/console_db/console_db.py
auto_archiver/modules/csv_db/__init__.py
auto_archiver/modules/csv_db/__manifest__.py
auto_archiver/modules/csv_db/csv_db.py
auto_archiver/modules/csv_feeder/__init__.py
auto_archiver/modules/csv_feeder/__manifest__.py
auto_archiver/modules/csv_feeder/csv_feeder.py
auto_archiver-1.2.0.dist-info/METADATA
auto_archiver-1.2.0.dist-info/WHEEL
auto_archiver-1.2.0.dist-info/entry_points.txt
auto_archiver-1.2.0.dist-info/licenses/LICENSE
auto_archiver-1.2.0.dist-info/RECORD
