Metadata-Version: 2.4
Name: auto-archiver
Version: 1.2.0
Summary: Automatically archive links to videos, images, and social media content from Google Sheets (and more).
License-Expression: MIT
License-File: LICENSE
Keywords: archive,oosi,osint,scraping
Author: Bellingcat
Author-email: tech@bellingcat.com
Requires-Python: >=3.10,<3.13
Classifier: Intended Audience :: Developers
Classifier: Intended Audience :: Science/Research
Classifier: License :: OSI Approved :: MIT License
Classifier: Programming Language :: Python :: 3
Requires-Dist: beautifulsoup4 (>=0.0.0)
Requires-Dist: bgutil-ytdlp-pot-provider (>=1.0.0)
Requires-Dist: boto3 (>=1.28.0,<2.0.0)
Requires-Dist: bs4 (>=0.0.0)
Requires-Dist: cryptography (>=46.0.3)
Requires-Dist: dataclasses-json (>=0.0.0)
Requires-Dist: dateparser (>=0.0.0)
Requires-Dist: ffmpeg-python (>=0.0.0)
Requires-Dist: google-api-python-client (>=0.0.0)
Requires-Dist: google-auth-httplib2 (>=0.0.0)
Requires-Dist: google-auth-oauthlib (>=0.0.0)
Requires-Dist: gspread (>=0.0.0)
Requires-Dist: instaloader (>=0.0.0)
Requires-Dist: jinja2 (>=0.0.0)
Requires-Dist: jsonlines (>=0.0.0)
Requires-Dist: loguru (>=0.0.0)
Requires-Dist: numpy (==2.1.3)
Requires-Dist: oauth2client (>=0.0.0)
Requires-Dist: opentimestamps (>=0.4.5,<0.5.0)
Requires-Dist: pdqhash (>=0.0.0)
Requires-Dist: pillow (>=0.0.0)
Requires-Dist: pyautogui (>=0.9.54,<0.10.0)
Requires-Dist: pyperclip (>=1.9.0)
Requires-Dist: pysubs2 (>=0.0.0)
Requires-Dist: python-slugify (>=0.0.0)
Requires-Dist: python-twitter-v2 (>=0.0.0)
Requires-Dist: requests[socks] (>=0.0.0)
Requires-Dist: retrying (>=0.0.0)
Requires-Dist: rfc3161-client (>=1.0.5)
Requires-Dist: rich-argparse (>=1.6.0,<2.0.0)
Requires-Dist: ruamel-yaml (>=0.18.10,<0.19.0)
Requires-Dist: secretstorage (>=3.3.3,<4.0.0)
Requires-Dist: seleniumbase (>=4.36.4,<5.0.0)
Requires-Dist: telethon (>=0.0.0)
Requires-Dist: tqdm (>=0.0.0)
Requires-Dist: warcio (>=0.0.0)
Requires-Dist: yt-dlp[curl-cffi,default] (>=2025.5.22,<2026.0.0)
Project-URL: Documentation, https://github.com/bellingcat/auto-archiver
Project-URL: Homepage, https://github.com/bellingcat/auto-archiver
Project-URL: Repository, https://github.com/bellingcat/auto-archiver
